straal/__init__.py
straal/base.py
straal/cards.py
straal/customers.py
straal/exceptions.py
straal/filters.py
straal/transactions.py
straal-0.2.0.dist-info/LICENSE
straal-0.2.0.dist-info/METADATA
straal-0.2.0.dist-info/WHEEL
straal-0.2.0.dist-info/top_level.txt
straal-0.2.0.dist-info/RECORD
